LICENSE.txt
MANIFEST.in
README.rst
setup.cfg
setup.py
199Fix.egg-info/PKG-INFO
199Fix.egg-info/SOURCES.txt
199Fix.egg-info/dependency_links.txt
199Fix.egg-info/requires.txt
199Fix.egg-info/top_level.txt
i99fix/__init__.py
i99fix/handlers.py