Metadata-Version: 1.1
Name: 199Fix
Version: 1.1.1
Summary: 199fix exception logger for Django
Home-page: https://github.com/199fix/199fix
Author: Madra David
Author-email: madra@199fix.com
License: MIT
Download-URL: https://github.com/199fix/199fix/tarball/0.2
Keywords: logging,uptime monitoring
Platform: UNKNOWN
Classifier: Development Status :: 5 - Production/Stable
Classifier: Environment :: Web Environment
Classifier: Framework :: Django
Classifier: Intended Audience :: Developers
Classifier: License :: OSI Approved :: MIT License
Classifier: Operating System :: OS Independent
Classifier: Programming Language :: Python
Classifier: Programming Language :: Python :: 2
Classifier: Programming Language :: Python :: 2.6
Classifier: Programming Language :: Python :: 2.7
Classifier: Programming Language :: Python :: 3
Classifier: Programming Language :: Python :: 3.2
Classifier: Programming Language :: Python :: 3.3
